transmiter/tx_sr.v
module tx_sr #(
    parameter DATA_W = 8,
    parameter FRAME_W = 10
) (
    input    wire                   clk,
    input    wire                   enable,
    input    wire   [DATA_W-1:0]    i_data,
    output   wire                   o_frame,
    output   wire                   o_txsr_empty

);

reg [FRAME_W-1:0] tx_shift_reg = 0;
reg [4:0] lvl_pointer = 0;
reg load_data = 0;

// Start of FSM
localparam [3:0] IDLE = 4'h0;
localparam [3:0]LOAD = 4'h1;
localparam [3:0]TXSHIFT = 4'h2;
reg [3:0] state = 0;
reg [3:0] next_state = 0;
wire transmit_stage;

always @(posedge clk ) begin
    state <= next_state;
end

always @(*) begin

    case (state)
        IDLE: begin
            if (enable) begin
                next_state = LOAD;
                load_data = 1;
            end else begin
                next_state = IDLE;
            end
        end 
        LOAD: begin
            next_state = TXSHIFT;
        end
        TXSHIFT: begin
            if (lvl_pointer > 5'd1) begin
                next_state = TXSHIFT;
            end else begin
                next_state = IDLE;
            end
        end
        default: next_state = IDLE;

    endcase
    
end

assign transmit_stage = (state == TXSHIFT) ? 1'b1 : 1'b0;



// End of FSM

always @(posedge clk ) begin
    if (load_data) begin
        tx_shift_reg <= {1'b1,i_data,1'b0}; //stop bit --- D7 to D0 --- start bit. Right shift , LSB first.
        lvl_pointer <= 5'd9;
        load_data <= 0;  
    end else if (transmit_stage) begin
        tx_shift_reg <= tx_shift_reg >> 1;
        lvl_pointer <= lvl_pointer - 1;
    end
end

assign o_frame = (transmit_stage) ? tx_shift_reg[0] : 1;
assign o_txsr_empty = (lvl_pointer == 0) ? 1 : 0;

endmodule

transmiter/tb_tx_sr.v
`timescale 1ns / 1ps

module tb_tx_sr;

    // Parameters
    parameter DATA_W = 8;
    parameter FRAME_W = 10;

    // Inputs
    reg clk;
    reg enable;
    reg [DATA_W-1:0] i_data;

    // Outputs
    wire o_frame;
    wire o_txsr_empty;

    // Instantiate the Unit Under Test (UUT)
    tx_sr #(
        .DATA_W(DATA_W),
        .FRAME_W(FRAME_W)
    ) uut (
        .clk(clk),
        .enable(enable),
        .i_data(i_data),
        .o_frame(o_frame),
        .o_txsr_empty(o_txsr_empty)
    );

    // Clock generation
    initial begin
        clk = 0;
        forever #5 clk = ~clk; // 10ns period clock
    end

    // Test sequence
    initial begin
        // Initialize Inputs
        enable = 0;
        i_data = 0;

        // Wait for global reset to finish
        #50;

        // Apply test vectors
        enable = 1;
        i_data = 8'b01001000; // Example data
        #250;

        enable = 0;
        i_data = 8'h3C;
        #20;

        enable = 1;
        i_data = 8'hFF;
        #20;

        // Add more test cases as needed
        // ...

        // End of test
        #100;
        $finish;
    end

    // Dump waves for GTKWave
    initial begin
        $dumpfile("tb_tx_sr.vcd");
        $dumpvars(0, tb_tx_sr);
    end

endmodule

transmiter/tb_tx_sr.vcd
$date
	Sat Jul 20 08:55:33 2024
$end
$version
	Icarus Verilog
$end
$timescale
	1ps
$end
$scope module tb_tx_sr $end
$var wire 1 ! o_txsr_empty $end
$var wire 1 " o_frame $end
$var reg 1 # clk $end
$var reg 1 $ enable $end
$var reg 8 % i_data [7:0] $end
$scope module uut $end
$var wire 1 # clk $end
$var wire 1 $ enable $end
$var wire 8 & i_data [7:0] $end
$var wire 1 ' transmit_stage $end
$var wire 1 ! o_txsr_empty $end
$var wire 1 " o_frame $end
$var reg 1 ( load_data $end
$var reg 5 ) lvl_pointer [4:0] $end
$var reg 4 * next_state [3:0] $end
$var reg 4 + state [3:0] $end
$var reg 10 , tx_shift_reg [9:0] $end
$upscope $end
$upscope $end
$enddefinitions $end
#0
$dumpvars
bx ,
b0 +
b0 *
bx )
0(
0'
b0 &
b0 %
0$
0#
1"
x!
$end
#5000
1#
#10000
0#
#15000
1#
#20000
0#
#25000
1#
#30000
0#
#35000
1#
#40000
0#
#45000
1#
#50000
1(
b1 *
0#
b1001000 %
b1001000 &
1$
#55000
0!
b10 *
0(
b1001 )
b1010010000 ,
b1 +
1#
#60000
0#
#65000
0"
1'
b10 +
1#
#70000
0#
#75000
b1000 )
b101001000 ,
1#
#80000
0#
#85000
b111 )
b10100100 ,
1#
#90000
0#
#95000
b110 )
b1010010 ,
1#
#100000
0#
#105000
1"
b101 )
b101001 ,
1#
#110000
0#
#115000
0"
b100 )
b10100 ,
1#
#120000
0#
#125000
b11 )
b1010 ,
1#
#130000
0#
#135000
1"
b10 )
b101 ,
1#
#140000
0#
#145000
0"
b0 *
b1 )
b10 ,
1#
#150000
0#
#155000
1"
1!
1(
b1 *
0'
b0 )
b1 ,
b0 +
1#
#160000
0#
#165000
0!
b10 *
b1 +
0(
b1001 )
b1010010000 ,
1#
#170000
0#
#175000
0"
1'
b10 +
1#
#180000
0#
#185000
b1000 )
b101001000 ,
1#
#190000
0#
#195000
b111 )
b10100100 ,
1#
#200000
0#
#205000
b110 )
b1010010 ,
1#
#210000
0#
#215000
1"
b101 )
b101001 ,
1#
#220000
0#
#225000
0"
b100 )
b10100 ,
1#
#230000
0#
#235000
b11 )
b1010 ,
1#
#240000
0#
#245000
1"
b10 )
b101 ,
1#
#250000
0#
#255000
0"
b0 *
b1 )
b10 ,
1#
#260000
0#
#265000
1"
1!
0'
1(
b1 *
b0 +
b0 )
b1 ,
1#
#270000
0#
#275000
0!
b10 *
0(
b1001 )
b1010010000 ,
b1 +
1#
#280000
0#
#285000
0"
1'
b10 +
1#
#290000
0#
#295000
b1000 )
b101001000 ,
1#
#300000
0#
b111100 %
b111100 &
0$
#305000
b111 )
b10100100 ,
1#
#310000
0#
#315000
b110 )
b1010010 ,
1#
#320000
0#
b11111111 %
b11111111 &
1$
#325000
1"
b101 )
b101001 ,
1#
#330000
0#
#335000
0"
b100 )
b10100 ,
1#
#340000
0#
#345000
b11 )
b1010 ,
1#
#350000
0#
#355000
1"
b10 )
b101 ,
1#
#360000
0#
#365000
0"
b0 *
b1 )
b10 ,
1#
#370000
0#
#375000
1"
1!
1(
b1 *
0'
b0 )
b1 ,
b0 +
1#
#380000
0#
#385000
0!
b10 *
b1 +
0(
b1001 )
b1111111110 ,
1#
#390000
0#
#395000
0"
1'
b10 +
1#
#400000
0#
#405000
1"
b1000 )
b111111111 ,
1#
#410000
0#
#415000
b111 )
b11111111 ,
1#
#420000
0#
#425000
b110 )
b1111111 ,
1#
#430000
0#
#435000
b101 )
b111111 ,
1#
